setup.py
usergrid_tools/__init__.py
usergrid_tools/library_check.py
usergrid_tools.egg-info/PKG-INFO
usergrid_tools.egg-info/SOURCES.txt
usergrid_tools.egg-info/dependency_links.txt
usergrid_tools.egg-info/entry_points.txt
usergrid_tools.egg-info/requires.txt
usergrid_tools.egg-info/top_level.txt
usergrid_tools/counters/__init__.py
usergrid_tools/counters/counter_test.py
usergrid_tools/general/__init__.py
usergrid_tools/general/deleter.py
usergrid_tools/general/duplicate_name_checker.py
usergrid_tools/general/queue_monitor.py
usergrid_tools/general/url_tester.py
usergrid_tools/general/user_confirm_activate.py
usergrid_tools/groups/__init__.py
usergrid_tools/groups/big_group_creater.py
usergrid_tools/import_export/__init__.py
usergrid_tools/import_export/usergrid_data_exporter.py
usergrid_tools/import_export/usergrid_data_importer.py
usergrid_tools/indexing/__init__.py
usergrid_tools/indexing/batch_index_test.py
usergrid_tools/indexing/entity_index_test.py
usergrid_tools/iterators/__init__.py
usergrid_tools/iterators/flexible_iterator.py
usergrid_tools/iterators/my_iterator.py
usergrid_tools/iterators/simple_iterator.py
usergrid_tools/iterators/target_test.py
usergrid_tools/iterators/usergrid_cross_region_iterator.py
usergrid_tools/iterators/usergrid_iterator.py
usergrid_tools/migration/__init__.py
usergrid_tools/migration/sample_data_loader.py
usergrid_tools/migration/usergrid_data_migrator.py
usergrid_tools/migration/usergrid_data_migrator_bad.py
usergrid_tools/parse_importer/__init__.py
usergrid_tools/parse_importer/parse_importer.py