Metadata-Version: 1.1
Name: usergrid-tools
Version: 1.2.3
Summary: Tools for working with Apache Usergrid
Home-page: http://usergrid.apache.org
Author: Jeff West
Author-email: jwest@apigee.com
License: UNKNOWN
Download-URL: https://codeload.github.com/jwest-apigee/usergrid-util-python/zip/1.2.3
Platform: UNKNOWN
